calamity_calendar/__init__.py
calamity_calendar/__main__.py
calamity_calendar/colors.py
calamity_calendar/command_tree.py
calamity_calendar/database.py
calamity_calendar/dateutils.py
calamity_calendar/display.py
calamity_calendar/getch.py
calamity_calendar/help.py
calamity_calendar/pager.py
calamity_calendar/validators.py
calamity_calendar-0.1.11.dist-info/METADATA
calamity_calendar-0.1.11.dist-info/WHEEL
calamity_calendar-0.1.11.dist-info/entry_points.txt
calamity_calendar-0.1.11.dist-info/RECORD
