Metadata-Version: 2.1
Name: calamity_calendar
Version: 0.1.11
Summary: 
Author: Oscar Laird
Author-email: olaird25@gmail.com
Requires-Python: >=3.8,<4.0
Classifier: Programming Language :: Python :: 3
Classifier: Programming Language :: Python :: 3.8
Classifier: Programming Language :: Python :: 3.9
Classifier: Programming Language :: Python :: 3.10
Classifier: Programming Language :: Python :: 3.11
Requires-Dist: fire (>=0.5.0,<0.6.0)
Requires-Dist: getch (>=1.0,<2.0)
Requires-Dist: pydevd (>=2.9.6,<3.0.0)
Requires-Dist: questionary (>=2.0.0,<3.0.0)
Requires-Dist: sqlalchemy (>=2.0.20,<3.0.0)
Requires-Dist: wcwidth (>=0.2.6,<0.3.0)
